ALU.v
module ALU (
    input [3:0] alu_code,
    input [15:0] reg_data1,
    input [15:0] reg_data2,
    output reg [15:0] accum,
    output reg pc_branch
);

always @(*) begin

accum = 16'b000000000000000;
pc_branch = 0;

    case(alu_code)
        4'b1000: accum = reg_data1 + reg_data2;
        4'b0100: accum = reg_data1 - reg_data2;
        4'b1111: begin
            if(reg_data1 == reg_data2) begin
                pc_branch = 1;
            end
        end
        4'b1101: begin
            if(reg_data1 < reg_data2) begin
                pc_branch = 1;
            end
        end
        4'b1110: begin
            if(reg_data1 > reg_data2) begin
                pc_branch = 1;
            end
        end
    endcase

end


endmodule

ALU_tb.v
`timescale 1ns / 1ps

module ALU_tb;

    reg [3:0] alu_code;
    reg [15:0] reg_data1;
    reg [15:0] reg_data2;
    wire [15:0] accum;
    wire pc_branch;

    ALU uut(
        .alu_code(alu_code),
        .reg_data1(reg_data1),
        .reg_data2(reg_data2),
        .accum(accum),
        .pc_branch(pc_branch)
    );

    initial begin
        $monitor("Time=%0t | alu_code=%b | reg1=%b | reg2=%b | accum=%b | pc_branch=%b",
                  $time, alu_code, reg_data1, reg_data2, accum, pc_branch);    
    
        alu_code = 4'b1000;
        reg_data1 = 16'b0000000000000001;
        reg_data2 = 16'b0000000000111111;
        #10;
        alu_code = 4'b0100;
        reg_data1 = 16'b0000000000111111;
        reg_data2 = 16'b0000000000000001;
        #10;
        alu_code = 4'b1100;
        reg_data1 = 16'b0000000000000001;
        reg_data2 = 16'b0000000000000001;
        #10;
        alu_code = 4'b1100;
        reg_data1 = 16'b0000000000000001;
        reg_data2 = 16'b0000000000000011;
        #10;
        alu_code = 4'b1101;
        reg_data1 = 16'b0000000000000001;
        reg_data2 = 16'b0000000000000011;
        #10;
        alu_code = 4'b1101;
        reg_data1 = 16'b0000000000000011;
        reg_data2 = 16'b0000000000000001;
        #10;
        alu_code = 4'b1110;
        reg_data1 = 16'b0000000000000001;
        reg_data2 = 16'b0000000000000011;
        #10;
        alu_code = 4'b1110;
        reg_data1 = 16'b0000000000000011;
        reg_data2 = 16'b0000000000000001;
        #10;
        #200;
        $finish;

    end
  
  	initial begin
      $dumpfile("ALU.vcd"); 
      $dumpvars(1, alu_code, reg_data1, reg_data2, accum, pc_branch);
      #200;
	end

endmodule

ALU.vcd
$date
	Thu Mar 27 00:53:03 2025
$end
$version
	Icarus Verilog
$end
$timescale
	1ps
$end
$scope module ALU_tb $end
$var reg 4 ! alu_code [3:0] $end
$upscope $end
$scope module ALU_tb $end
$var reg 16 " reg_data1 [15:0] $end
$upscope $end
$scope module ALU_tb $end
$var reg 16 # reg_data2 [15:0] $end
$upscope $end
$scope module ALU_tb $end
$var wire 16 $ accum [15:0] $end
$upscope $end
$scope module ALU_tb $end
$var wire 1 % pc_branch $end
$upscope $end
$enddefinitions $end
$comment Show the parameter values. $end
$dumpall
$end
#0
$dumpvars
0%
b1000000 $
b111111 #
b1 "
b1000 !
$end
#10000
b111110 $
b1 #
b111111 "
b100 !
#20000
b0 $
b1 "
b1100 !
#30000
b11 #
#40000
1%
b1101 !
#50000
0%
b1 #
b11 "
#60000
b11 #
b1 "
b1110 !
#70000
1%
b1 #
b11 "
