Program_counter.v
module Program_counter(
    input clk,
    input reset,
    input jump,
    input [7:0] jump_adr,
    input branch,
    input [7:0] branch_adr,
    output reg [7:0] address
);

reg [7:0] program; //register where the current RAM adress is loaded after each clock cycle

always @(posedge clk)
    if(reset) begin
        program <= 8'b00000000;
    end
    else if(jump)begin //Handles the case if the current instrcution is jump and skips to input adress
        program <= jump_adr;
    end
    else if(branch)begin //Handles the case if the current instrcution is branch and skips to input adress
        program <= branch_adr;
    end
    else begin
        program <= program + 1; //Normal 1 incrementer
    end

always @(program) begin
    address = program; //output is the program adress register
end

endmodule

Program_counter_tb.v
module Program_counter_tb;
    reg clk;
    reg reset;
    reg jump;
    reg [7:0] jump_adr;
    reg branch;
    reg [7:0] branch_adr;
    wire [7:0] address;

    Program_counter uut(
        .clk(clk),
        .reset(reset),
        .jump(jump),
        .jump_adr(jump_adr),
        .branch(branch),
        .branch_adr(branch_adr),
        .address(address)
    );

    initial begin
        clk = 0;      
        reset = 1;    
        jump = 0;
        jump_adr = 8'b00000000; 
        branch = 0;
        branch_adr = 8'b00000000; 
    end


    always #5 clk = ~clk; 

    initial begin

        $monitor("Time=%0t | jump=%b | branch=%b | address=%b",
                  $time, jump, branch, address);

        #10;
        reset = 0;
        #10;#10;#10;#10;#10;#10;
        jump = 1;
        jump_adr = 8'b00000001;
        #10;
        jump = 0;
        #10;#10;#10;#10;
        branch = 1;
        branch_adr = 8'b10000000;
        #10;
        branch = 0;
        #10;#10;#10;#10;
        $finish;     

    end

    initial begin
    	$dumpfile("program_counter.vcd"); 
    	$dumpvars(1, clk, reset, jump, jump_adr, branch, branch_adr, 							address);
      	#200;
	end

endmodule

program_counter.vcd
$date
	Thu Mar 27 00:48:19 2025
$end
$version
	Icarus Verilog
$end
$timescale
	1s
$end
$scope module Program_counter_tb $end
$var reg 1 ! clk $end
$upscope $end
$scope module Program_counter_tb $end
$var reg 1 " reset $end
$upscope $end
$scope module Program_counter_tb $end
$var reg 1 # jump $end
$upscope $end
$scope module Program_counter_tb $end
$var reg 8 $ jump_adr [7:0] $end
$upscope $end
$scope module Program_counter_tb $end
$var reg 1 % branch $end
$upscope $end
$scope module Program_counter_tb $end
$var reg 8 & branch_adr [7:0] $end
$upscope $end
$scope module Program_counter_tb $end
$var wire 8 ' address [7:0] $end
$upscope $end
$enddefinitions $end
$comment Show the parameter values. $end
$dumpall
$end
#0
$dumpvars
bx '
b0 &
0%
b0 $
0#
1"
0!
$end
#5
b0 '
1!
#10
0!
0"
#15
b1 '
1!
#20
0!
#25
b10 '
1!
#30
0!
#35
b11 '
1!
#40
0!
#45
b100 '
1!
#50
0!
#55
b101 '
1!
#60
0!
#65
b110 '
1!
#70
0!
b1 $
1#
#75
b1 '
1!
#80
0!
0#
#85
b10 '
1!
#90
0!
#95
b11 '
1!
#100
0!
#105
b100 '
1!
#110
0!
#115
b101 '
1!
#120
0!
b10000000 &
1%
#125
b10000000 '
1!
#130
0!
0%
#135
b10000001 '
1!
#140
0!
#145
b10000010 '
1!
#150
0!
#155
b10000011 '
1!
#160
0!
#165
b10000100 '
1!
